{
    "Landsknecht": {
        "skills":[
            "HpUpL",
            "TpUpL",
            "StrUpL",
            "VitUpL",
            "TecUpL",
            "AgiUpL",
            "LucUpL",
            "EscUpL",
            "SwordsL",
            "Axes",
            "Counter",
            "2HitL",
            "Cleaver",
            "Tornado",
            "Allslash",
            "Hypercut",
            "Riskcut",
            "Deathaxe",
            "Silencer",
            "Brawn",
            "Lifeaxe",
            "Stunner",
            "Blazer",
            "Freezer",
            "Shocker",
            "WarCry",
            "Unbound",
            "MineL",
            "AllOut"
        ]
    },
     "Survivalist": {
        "skills":[
            "HpUpS",
            "TpUpS",
            "StrUpS",
            "VitUpS",
            "TecUpS",
            "AgiUpS",
            "LucUpS",
            "EscUpS",
            "Bows",
            "Ambush",
            "Sagacity",
            "1stHit",
            "Trueshot",
            "2Bolt",
            "Sleeper",
            "Number",
            "Poisoner",
            "Apollon",
            "1stTurn",
            "Slowstep",
            "Baitstep",
            "Velocity",
            "PatrolS",
            "Stalker",
            "Foesense",
            "TakeS",
            "ChopS",
            "MineS",
            "Airwalk"
        ]
    },
    "Protector": {
        "skills":[
            "HpUpP",
            "TpUpP",
            "StrUpP",
            "VitUpP",
            "TecUpP",
            "AgiUpP",
            "LucUpP",
            "EscUpP",
            "Shields",
            "Aegis",
            "En GardeP",
            "HP Regen",
            "Riskwall",
            "Smite",
            "Front Guard",
            "Back Guard",
            "All Guard",
            "1 Guard",
            "Antifire",
            "Anticold",
            "Antivolt",
            "Antiall",
            "Fortify",
            "Provoke",
            "Parry",
            "RefreshP",
            "Flee",
            "MineP",
            "Painless"
        ]
    },
    "Dark Hunter": {
        "skills":[
            "HpUpD",
            "TpUpD",
            "StrUpD",
            "VitUpD",
            "TecUpD",
            "AgiUpD",
            "LucUpD",
            "EscUpD",
            "Whips",
            "SwordsD",
            "Antisick",
            "Antibind",
            "Viper",
            "Shackles",
            "Cuffs",
            "Gag",
            "Ecstasy",
            "Climax",
            "Hypnos",
            "Nerve",
            "Mirage",
            "Drain",
            "Petrify",
            "Bait",
            "Magibait",
            "UnbindD",
            "Racket",
            "ChopD",
            "Dominate"
        ]
    },
    "Medic": {
        "skills":[
            "HpUpM",
            "TpUpM",
            "StrUpM",
            "VitUpM",
            "TecUpM",
            "AgiUpM",
            "LucUpM",
            "EscUpM",
            "Healer",
            "Patch Up",
            "TP Regen",
            "ScavengeM",
            "CureM",
            "Cure 2M",
            "Cure 3M",
            "SalveM",
            "Salve 2M",
            "Salve 3",
            "Revive",
            "UnbindM",
            "Freedom",
            "RefreshM",
            "Purify",
            "Caduceus",
            "CPR",
            "Phoenix",
            "PatrolM",
            "TakeM",
            "H. Touch"
        ]
    },
    "Alchemist": {
        "skills":[
            "HpUpA",
            "TpUpA",
            "StrUpA",
            "VitUpA",
            "TecUpA",
            "AgiUpA",
            "LucUpA",
            "EscUpA",
            "Fire Up",
            "Ice Up",
            "Volt Up",
            "Phys Up",
            "Fire",
            "Ice",
            "Volt",
            "Flame",
            "Freeze",
            "Thunder",
            "Inferno",
            "Cocytus",
            "Thor",
            "Blades",
            "Gravity",
            "Piercing",
            "Megido",
            "Return",
            "Analysis",
            "Eschaton",
            "TakeA"
        ]
    },
    "Troubadour": {
        "skills":[
            "HpUpT",
            "TpUpT",
            "StrUpT",
            "VitUpT",
            "TecUpT",
            "AgiUpT",
            "LucUpT",
            "EscUpT",
            "Songs",
            "Divinity",
            "Bravery",
            "Shelter",
            "Mercury",
            "Stamina",
            "Blaze",
            "Frost",
            "Shock",
            "Ifrit",
            "Ymir",
            "Taranis",
            "Erasure",
            "Nihilo",
            "Health",
            "Recovery",
            "Danger",
            "Luring",
            "Slumber",
            "TakeT",
            "Crusade"
        ]
    },
    "Ronin": {
        "skills":[
            "HpUpR",
            "TpUpR",
            "StrUpR",
            "VitUpR",
            "TecUpR",
            "AgiUpR",
            "LucUpR",
            "EscUpR",
            "Shiraha",
            "Overhead",
            "Seigan",
            "Iai",
            "Clarity",
            "Sayageki",
            "Zamba",
            "Midareba",
            "Koteuchi",
            "Getsuei",
            "Kubiuchi",
            "Nukechi",
            "Orochi",
            "Raizuki",
            "Hyosetsu",
            "Kienzan",
            "Minakata",
            "Hosoyuki",
            "Dead Law",
            "MineR",
            "Issen"
        ]
    },
     "Hexer": {
        "skills":[
            "HpUpH",
            "TpUpH",
            "StrUpH",
            "VitUpH",
            "TecUpH",
            "AgiUpH",
            "LucUpH",
            "EscUpH",
            "Curses",
            "ScavengeH",
            "Sapping",
            "Frailty",
            "Leaden",
            "Dampen",
            "Cranial",
            "Abdomen",
            "Immobile",
            "Blinding",
            "Torpor",
            "Evil Eye",
            "Paralysis",
            "Corrupt",
            "Poison",
            "Suicide",
            "Betrayal",
            "Paralyze",
            "Revenge",
            "TakeH",
            "Caprice"
        ]
    },
    "Gunner": {
        "skills":[
            "HpUpG",
            "TpUpG",
            "StrUpG",
            "VitUpG",
            "TecUpG",
            "AgiUpG",
            "LucUpG",
            "EscUpG",
            "Guns",
            "2HitG",
            "Weakshot",
            "Legshot",
            "Armshot",
            "Headshot",
            "Riskshot",
            "Stunshot",
            "Snipe",
            "Fireshot",
            "Iceshot",
            "Voltshot",
            "Riskfire",
            "Riskice",
            "Riskvolt",
            "Wildshot",
            "Ricochet",
            "Medishot",
            "Haltshot",
            "TakeG",
            "Riot Gun"
        ]
    },
    "War Magus": {
        "skills":[
            "HpUpW",
            "TpUpW",
            "StrUpW",
            "VitUpW",
            "TecUpW",
            "AgiUpW",
            "LucUpW",
            "EscUpW",
            "War Edge",
            "War Lore",
            "Regenall",
            "Blindcut",
            "Venomcut",
            "Stuncut",
            "Sleepcut",
            "Fearcut",
            "Cursecut",
            "CureW",
            "Cure 2W",
            "Cure 3W",
            "SalveW",
            "Salve 2W",
            "Warmight",
            "Rockskin",
            "Elkspeed",
            "Erase",
            "Transfer",
            "ChopW",
            "Invoke"
        ]
    },
    "Beast": {
        "skills":[
            "HpUpS",
            "TpUpS",
            "StrUpS",
            "VitUpS",
            "TecUpS",
            "AgiUpS",
            "LucUpS",
            "EscUpS",
            "Loyalty",
            "Autocure",
            "Autoheal",
            "En Garde",
            "Tenacity",
            "Maul",
            "Devour",
            "Bodyslam",
            "Rampage",
            "Claw",
            "Wildcut",
            "Bristle",
            "Preen",
            "Wildwall",
            "Roar",
            "Saliva",
            "Doze Off",
            "Howl",
            "Growl",
            "Fetch",
            "Salivall"
        ]
    }
}